Metadata-Version: 1.0
Name: bibby
Version: 0.1
Summary: Small python library and CLI for doing stuff with Bibsonomy
Home-page: https://github.com/salotz/bibby
Author: Samuel D. Lotz
Author-email: samuel.lotz@salotz.info
License: UNKNOWN
Platform: UNKNOWN
